<?xml version="1.0" encoding="utf-8"?>
<TransXChange xmlns:xsi="http://www.w3.org/2001/XMLSchema-instance" xmlns:xsd="http://www.w3.org/2001/XMLSchema" CreationDateTime="2024-08-02T12:39:39" ModificationDateTime="2024-08-02T12:39:39" Modification="new" RevisionNumber="1" FileName="F034-SIF--SCFI-ST-2023-08-14-Fife_Timeplan_09_1408_1908-Transmill.xml" SchemaVersion="2.5" RegistrationDocument="true" xsi:schemaLocation="http://www.transxchange.org.uk/ http://www.transxchange.org.uk/schema/2.5/TransXChange_general.xsd" xmlns="http://www.transxchange.org.uk/">
  <StopPoints>
    <AnnotatedStopPointRef>
      <StopPointRef>6500K0034</StopPointRef>
      <CommonName>Carron Place</CommonName>
      <LocalityName>Torbain</LocalityName>
      <LocalityQualifier>Kirkcaldy</LocalityQualifier>
    </AnnotatedStopPointRef>
    <AnnotatedStopPointRef>
      <StopPointRef>6500K0041</StopPointRef>
      <CommonName>Lindores Drive</CommonName>
      <LocalityName>Torbain</LocalityName>
      <LocalityQualifier>Kirkcaldy</LocalityQualifier>
    </AnnotatedStopPointRef>
    <AnnotatedStopPointRef>
      <StopPointRef>6500K0057</StopPointRef>
      <CommonName>Birnam Road Shops</CommonName>
      <LocalityName>Templehall</LocalityName>
      <LocalityQualifier>Kirkcaldy</LocalityQualifier>
    </AnnotatedStopPointRef>
    <AnnotatedStopPointRef>
      <StopPointRef>6500K0065</StopPointRef>
      <CommonName>Maree Place</CommonName>
      <LocalityName>Torbain</LocalityName>
      <LocalityQualifier>Kirkcaldy</LocalityQualifier>
    </AnnotatedStopPointRef>
    <AnnotatedStopPointRef>
      <StopPointRef>6500K0070</StopPointRef>
      <CommonName>Harris Drive</CommonName>
      <LocalityName>Torbain</LocalityName>
      <LocalityQualifier>Kirkcaldy</LocalityQualifier>
    </AnnotatedStopPointRef>
    <AnnotatedStopPointRef>
      <StopPointRef>6500K0082</StopPointRef>
      <CommonName>Cawdor Crescent</CommonName>
      <LocalityName>Torbain</LocalityName>
      <LocalityQualifier>Kirkcaldy</LocalityQualifier>
    </AnnotatedStopPointRef>
    <AnnotatedStopPointRef>
      <StopPointRef>6500K0084</StopPointRef>
      <CommonName>Templehall Shops</CommonName>
      <LocalityName>Templehall</LocalityName>
      <LocalityQualifier>Kirkcaldy</LocalityQualifier>
    </AnnotatedStopPointRef>
    <AnnotatedStopPointRef>
      <StopPointRef>6500K0086</StopPointRef>
      <CommonName>Dunearn Drive</CommonName>
      <LocalityName>Templehall</LocalityName>
      <LocalityQualifier>Kirkcaldy</LocalityQualifier>
    </AnnotatedStopPointRef>
    <AnnotatedStopPointRef>
      <StopPointRef>6500K0087</StopPointRef>
      <CommonName>The Buccaneer</CommonName>
      <LocalityName>Templehall</LocalityName>
      <LocalityQualifier>Kirkcaldy</LocalityQualifier>
    </AnnotatedStopPointRef>
    <AnnotatedStopPointRef>
      <StopPointRef>6500K0090</StopPointRef>
      <CommonName>Sidlaw Street</CommonName>
      <LocalityName>Templehall</LocalityName>
      <LocalityQualifier>Kirkcaldy</LocalityQualifier>
    </AnnotatedStopPointRef>
    <AnnotatedStopPointRef>
      <StopPointRef>6500K0091</StopPointRef>
      <CommonName>Cramond Gardens</CommonName>
      <LocalityName>Templehall</LocalityName>
      <LocalityQualifier>Kirkcaldy</LocalityQualifier>
    </AnnotatedStopPointRef>
    <AnnotatedStopPointRef>
      <StopPointRef>6500K0094</StopPointRef>
      <CommonName>Cheviot Road</CommonName>
      <LocalityName>Templehall</LocalityName>
      <LocalityQualifier>Kirkcaldy</LocalityQualifier>
    </AnnotatedStopPointRef>
    <AnnotatedStopPointRef>
      <StopPointRef>6500K0096</StopPointRef>
      <CommonName>White Heather</CommonName>
      <LocalityName>Hayfield</LocalityName>
      <LocalityQualifier>Kirkcaldy</LocalityQualifier>
    </AnnotatedStopPointRef>
    <AnnotatedStopPointRef>
      <StopPointRef>6500K0211</StopPointRef>
      <CommonName>Morven Grove</CommonName>
      <LocalityName>Sauchenbush</LocalityName>
      <LocalityQualifier>Kirkcaldy</LocalityQualifier>
    </AnnotatedStopPointRef>
    <AnnotatedStopPointRef>
      <StopPointRef>6500K0213</StopPointRef>
      <CommonName>Valley Gardens Park</CommonName>
      <LocalityName>Sauchenbush</LocalityName>
      <LocalityQualifier>Kirkcaldy</LocalityQualifier>
    </AnnotatedStopPointRef>
    <AnnotatedStopPointRef>
      <StopPointRef>6500K0216</StopPointRef>
      <CommonName>Valley Gardens South</CommonName>
      <LocalityName>Sauchenbush</LocalityName>
      <LocalityQualifier>Kirkcaldy</LocalityQualifier>
    </AnnotatedStopPointRef>
    <AnnotatedStopPointRef>
      <StopPointRef>6500K0218</StopPointRef>
      <CommonName>Hendry Crescent</CommonName>
      <LocalityName>Sauchenbush</LocalityName>
      <LocalityQualifier>Kirkcaldy</LocalityQualifier>
    </AnnotatedStopPointRef>
    <AnnotatedStopPointRef>
      <StopPointRef>6500K0219</StopPointRef>
      <CommonName>Winifred Crescent</CommonName>
      <LocalityName>Sauchenbush</LocalityName>
      <LocalityQualifier>Kirkcaldy</LocalityQualifier>
    </AnnotatedStopPointRef>
    <AnnotatedStopPointRef>
      <StopPointRef>6500K0221</StopPointRef>
      <CommonName>Mormon Church</CommonName>
      <LocalityName>Sauchenbush</LocalityName>
      <LocalityQualifier>Kirkcaldy</LocalityQualifier>
    </AnnotatedStopPointRef>
    <AnnotatedStopPointRef>
      <StopPointRef>6500K0227</StopPointRef>
      <CommonName>Forth Park Drive</CommonName>
      <LocalityName>Sauchenbush</LocalityName>
      <LocalityQualifier>Kirkcaldy</LocalityQualifier>
    </AnnotatedStopPointRef>
    <AnnotatedStopPointRef>
      <StopPointRef>6500K0230</StopPointRef>
      <CommonName>Laurel Crescent</CommonName>
      <LocalityName>Hayfield</LocalityName>
      <LocalityQualifier>Kirkcaldy</LocalityQualifier>
    </AnnotatedStopPointRef>
    <AnnotatedStopPointRef>
      <StopPointRef>6500K0233</StopPointRef>
      <CommonName>Kennedy Crescent</CommonName>
      <LocalityName>Kirkcaldy</LocalityName>
      <LocalityQualifier>Kirkcaldy</LocalityQualifier>
    </AnnotatedStopPointRef>
    <AnnotatedStopPointRef>
      <StopPointRef>6500K0235</StopPointRef>
      <CommonName>King Street</CommonName>
      <LocalityName>Kirkcaldy</LocalityName>
      <LocalityQualifier>Kirkcaldy</LocalityQualifier>
    </AnnotatedStopPointRef>
    <AnnotatedStopPointRef>
      <StopPointRef>6500K0237</StopPointRef>
      <CommonName>Legion Court</CommonName>
      <LocalityName>Kirkcaldy</LocalityName>
      <LocalityQualifier>Kirkcaldy</LocalityQualifier>
    </AnnotatedStopPointRef>
    <AnnotatedStopPointRef>
      <StopPointRef>6500K0293</StopPointRef>
      <CommonName>Bennochy Bridge</CommonName>
      <LocalityName>Kirkcaldy</LocalityName>
      <LocalityQualifier>Kirkcaldy</LocalityQualifier>
    </AnnotatedStopPointRef>
    <AnnotatedStopPointRef>
      <StopPointRef>6500K0303</StopPointRef>
      <CommonName>Railway Station Stance C</CommonName>
      <LocalityName>Kirkcaldy</LocalityName>
      <LocalityQualifier>Kirkcaldy</LocalityQualifier>
    </AnnotatedStopPointRef>
    <AnnotatedStopPointRef>
      <StopPointRef>6500K0304</StopPointRef>
      <CommonName>Railway Station Stance D</CommonName>
      <LocalityName>Kirkcaldy</LocalityName>
      <LocalityQualifier>Kirkcaldy</LocalityQualifier>
    </AnnotatedStopPointRef>
    <AnnotatedStopPointRef>
      <StopPointRef>6500K0305</StopPointRef>
      <CommonName>Adam Smith Theatre</CommonName>
      <LocalityName>Kirkcaldy</LocalityName>
      <LocalityQualifier>Kirkcaldy</LocalityQualifier>
    </AnnotatedStopPointRef>
    <AnnotatedStopPointRef>
      <StopPointRef>6500K1087</StopPointRef>
      <CommonName>Atholl Terrace</CommonName>
      <LocalityName>Torbain</LocalityName>
      <LocalityQualifier>Kirkcaldy</LocalityQualifier>
    </AnnotatedStopPointRef>
    <AnnotatedStopPointRef>
      <StopPointRef>6500K1089</StopPointRef>
      <CommonName>Birnam Road</CommonName>
      <LocalityName>Torbain</LocalityName>
      <LocalityQualifier>Kirkcaldy</LocalityQualifier>
    </AnnotatedStopPointRef>
    <AnnotatedStopPointRef>
      <StopPointRef>6500K1091</StopPointRef>
      <CommonName>Lismore Place</CommonName>
      <LocalityName>Templehall</LocalityName>
      <LocalityQualifier>Kirkcaldy</LocalityQualifier>
    </AnnotatedStopPointRef>
    <AnnotatedStopPointRef>
      <StopPointRef>6500K1093</StopPointRef>
      <CommonName>Lismore Avenue</CommonName>
      <LocalityName>Templehall</LocalityName>
      <LocalityQualifier>Kirkcaldy</LocalityQualifier>
    </AnnotatedStopPointRef>
    <AnnotatedStopPointRef>
      <StopPointRef>6500K1094</StopPointRef>
      <CommonName>Ailsa Grove</CommonName>
      <LocalityName>Templehall</LocalityName>
      <LocalityQualifier>Kirkcaldy</LocalityQualifier>
    </AnnotatedStopPointRef>
    <AnnotatedStopPointRef>
      <StopPointRef>6500K1096</StopPointRef>
      <CommonName>Davaar Drive</CommonName>
      <LocalityName>Templehall</LocalityName>
      <LocalityQualifier>Kirkcaldy</LocalityQualifier>
    </AnnotatedStopPointRef>
    <AnnotatedStopPointRef>
      <StopPointRef>6500K1307</StopPointRef>
      <CommonName>Bus Station</CommonName>
      <LocalityName>Kirkcaldy</LocalityName>
      <LocalityQualifier>Kirkcaldy</LocalityQualifier>
    </AnnotatedStopPointRef>
    <AnnotatedStopPointRef>
      <StopPointRef>6500K1497</StopPointRef>
      <CommonName>Kenmore Terrace</CommonName>
      <LocalityName>Torbain</LocalityName>
      <LocalityQualifier>Kirkcaldy</LocalityQualifier>
    </AnnotatedStopPointRef>
    <AnnotatedStopPointRef>
      <StopPointRef>6500K9026</StopPointRef>
      <CommonName>Inchgarvie Road</CommonName>
      <LocalityName>Templehall</LocalityName>
      <LocalityQualifier>Kirkcaldy</LocalityQualifier>
    </AnnotatedStopPointRef>
    <AnnotatedStopPointRef>
      <StopPointRef>6500K9301</StopPointRef>
      <CommonName>Bus Station</CommonName>
      <LocalityName>Kirkcaldy</LocalityName>
      <LocalityQualifier>Kirkcaldy</LocalityQualifier>
    </AnnotatedStopPointRef>
  </StopPoints>
  <RouteSections>
    <RouteSection id="RS1">
      <RouteLink id="RL1">
        <From>
          <StopPointRef>6500K1307</StopPointRef>
        </From>
        <To>
          <StopPointRef>6500K0303</StopPointRef>
        </To>
        <Distance>581</Distance>
        <Direction>outbound</Direction>
      </RouteLink>
      <RouteLink id="RL2">
        <From>
          <StopPointRef>6500K0303</StopPointRef>
        </From>
        <To>
          <StopPointRef>6500K0227</StopPointRef>
        </To>
        <Distance>724</Distance>
        <Direction>outbound</Direction>
      </RouteLink>
      <RouteLink id="RL3">
        <From>
          <StopPointRef>6500K0227</StopPointRef>
        </From>
        <To>
          <StopPointRef>6500K0221</StopPointRef>
        </To>
        <Distance>379</Distance>
        <Direction>outbound</Direction>
      </RouteLink>
      <RouteLink id="RL4">
        <From>
          <StopPointRef>6500K0221</StopPointRef>
        </From>
        <To>
          <StopPointRef>6500K0219</StopPointRef>
        </To>
        <Distance>199</Distance>
        <Direction>outbound</Direction>
      </RouteLink>
      <RouteLink id="RL5">
        <From>
          <StopPointRef>6500K0219</StopPointRef>
        </From>
        <To>
          <StopPointRef>6500K0218</StopPointRef>
        </To>
        <Distance>280</Distance>
        <Direction>outbound</Direction>
      </RouteLink>
      <RouteLink id="RL6">
        <From>
          <StopPointRef>6500K0218</StopPointRef>
        </From>
        <To>
          <StopPointRef>6500K0216</StopPointRef>
        </To>
        <Distance>231</Distance>
        <Direction>outbound</Direction>
      </RouteLink>
      <RouteLink id="RL7">
        <From>
          <StopPointRef>6500K0216</StopPointRef>
        </From>
        <To>
          <StopPointRef>6500K0213</StopPointRef>
        </To>
        <Distance>288</Distance>
        <Direction>outbound</Direction>
      </RouteLink>
      <RouteLink id="RL8">
        <From>
          <StopPointRef>6500K0213</StopPointRef>
        </From>
        <To>
          <StopPointRef>6500K0211</StopPointRef>
        </To>
        <Distance>206</Distance>
        <Direction>outbound</Direction>
      </RouteLink>
      <RouteLink id="RL9">
        <From>
          <StopPointRef>6500K0211</StopPointRef>
        </From>
        <To>
          <StopPointRef>6500K0086</StopPointRef>
        </To>
        <Distance>266</Distance>
        <Direction>outbound</Direction>
      </RouteLink>
      <RouteLink id="RL10">
        <From>
          <StopPointRef>6500K0086</StopPointRef>
        </From>
        <To>
          <StopPointRef>6500K0084</StopPointRef>
        </To>
        <Distance>200</Distance>
        <Direction>outbound</Direction>
      </RouteLink>
      <RouteLink id="RL11">
        <From>
          <StopPointRef>6500K0084</StopPointRef>
        </From>
        <To>
          <StopPointRef>6500K0082</StopPointRef>
        </To>
        <Distance>221</Distance>
        <Direction>outbound</Direction>
      </RouteLink>
      <RouteLink id="RL12">
        <From>
          <StopPointRef>6500K0082</StopPointRef>
        </From>
        <To>
          <StopPointRef>6500K1087</StopPointRef>
        </To>
        <Distance>338</Distance>
        <Direction>outbound</Direction>
      </RouteLink>
      <RouteLink id="RL13">
        <From>
          <StopPointRef>6500K1087</StopPointRef>
        </From>
        <To>
          <StopPointRef>6500K1497</StopPointRef>
        </To>
        <Distance>217</Distance>
        <Direction>outbound</Direction>
      </RouteLink>
      <RouteLink id="RL14">
        <From>
          <StopPointRef>6500K1497</StopPointRef>
        </From>
        <To>
          <StopPointRef>6500K1089</StopPointRef>
        </To>
        <Distance>158</Distance>
        <Direction>outbound</Direction>
      </RouteLink>
      <RouteLink id="RL15">
        <From>
          <StopPointRef>6500K1089</StopPointRef>
        </From>
        <To>
          <StopPointRef>6500K0057</StopPointRef>
        </To>
        <Distance>186</Distance>
        <Direction>outbound</Direction>
      </RouteLink>
      <RouteLink id="RL16">
        <From>
          <StopPointRef>6500K0057</StopPointRef>
        </From>
        <To>
          <StopPointRef>6500K0041</StopPointRef>
        </To>
        <Distance>230</Distance>
        <Direction>outbound</Direction>
      </RouteLink>
      <RouteLink id="RL17">
        <From>
          <StopPointRef>6500K0041</StopPointRef>
        </From>
        <To>
          <StopPointRef>6500K0034</StopPointRef>
        </To>
        <Distance>260</Distance>
        <Direction>outbound</Direction>
      </RouteLink>
      <RouteLink id="RL18">
        <From>
          <StopPointRef>6500K0034</StopPointRef>
        </From>
        <To>
          <StopPointRef>6500K0065</StopPointRef>
        </To>
        <Distance>96</Distance>
        <Direction>outbound</Direction>
      </RouteLink>
      <RouteLink id="RL19">
        <From>
          <StopPointRef>6500K0065</StopPointRef>
        </From>
        <To>
          <StopPointRef>6500K0070</StopPointRef>
        </To>
        <Distance>415</Distance>
        <Direction>outbound</Direction>
      </RouteLink>
      <RouteLink id="RL20">
        <From>
          <StopPointRef>6500K0070</StopPointRef>
        </From>
        <To>
          <StopPointRef>6500K9026</StopPointRef>
        </To>
        <Distance>114</Distance>
        <Direction>outbound</Direction>
      </RouteLink>
      <RouteLink id="RL21">
        <From>
          <StopPointRef>6500K9026</StopPointRef>
        </From>
        <To>
          <StopPointRef>6500K1096</StopPointRef>
        </To>
        <Distance>313</Distance>
        <Direction>outbound</Direction>
      </RouteLink>
      <RouteLink id="RL22">
        <From>
          <StopPointRef>6500K1096</StopPointRef>
        </From>
        <To>
          <StopPointRef>6500K1094</StopPointRef>
        </To>
        <Distance>297</Distance>
        <Direction>outbound</Direction>
      </RouteLink>
      <RouteLink id="RL23">
        <From>
          <StopPointRef>6500K1094</StopPointRef>
        </From>
        <To>
          <StopPointRef>6500K1093</StopPointRef>
        </To>
        <Distance>260</Distance>
        <Direction>outbound</Direction>
      </RouteLink>
      <RouteLink id="RL24">
        <From>
          <StopPointRef>6500K1093</StopPointRef>
        </From>
        <To>
          <StopPointRef>6500K1091</StopPointRef>
        </To>
        <Distance>268</Distance>
        <Direction>outbound</Direction>
      </RouteLink>
      <RouteLink id="RL25">
        <From>
          <StopPointRef>6500K1091</StopPointRef>
        </From>
        <To>
          <StopPointRef>6500K0087</StopPointRef>
        </To>
        <Distance>173</Distance>
        <Direction>outbound</Direction>
      </RouteLink>
      <RouteLink id="RL26">
        <From>
          <StopPointRef>6500K0087</StopPointRef>
        </From>
        <To>
          <StopPointRef>6500K0090</StopPointRef>
        </To>
        <Distance>179</Distance>
        <Direction>outbound</Direction>
      </RouteLink>
      <RouteLink id="RL27">
        <From>
          <StopPointRef>6500K0090</StopPointRef>
        </From>
        <To>
          <StopPointRef>6500K0091</StopPointRef>
        </To>
        <Distance>318</Distance>
        <Direction>outbound</Direction>
      </RouteLink>
      <RouteLink id="RL28">
        <From>
          <StopPointRef>6500K0091</StopPointRef>
        </From>
        <To>
          <StopPointRef>6500K0094</StopPointRef>
        </To>
        <Distance>371</Distance>
        <Direction>outbound</Direction>
      </RouteLink>
      <RouteLink id="RL29">
        <From>
          <StopPointRef>6500K0094</StopPointRef>
        </From>
        <To>
          <StopPointRef>6500K0096</StopPointRef>
        </To>
        <Distance>291</Distance>
        <Direction>outbound</Direction>
      </RouteLink>
      <RouteLink id="RL30">
        <From>
          <StopPointRef>6500K0096</StopPointRef>
        </From>
        <To>
          <StopPointRef>6500K0230</StopPointRef>
        </To>
        <Distance>224</Distance>
        <Direction>outbound</Direction>
      </RouteLink>
      <RouteLink id="RL31">
        <From>
          <StopPointRef>6500K0230</StopPointRef>
        </From>
        <To>
          <StopPointRef>6500K0233</StopPointRef>
        </To>
        <Distance>193</Distance>
        <Direction>outbound</Direction>
      </RouteLink>
      <RouteLink id="RL32">
        <From>
          <StopPointRef>6500K0233</StopPointRef>
        </From>
        <To>
          <StopPointRef>6500K0235</StopPointRef>
        </To>
        <Distance>215</Distance>
        <Direction>outbound</Direction>
      </RouteLink>
      <RouteLink id="RL33">
        <From>
          <StopPointRef>6500K0235</StopPointRef>
        </From>
        <To>
          <StopPointRef>6500K0237</StopPointRef>
        </To>
        <Distance>548</Distance>
        <Direction>outbound</Direction>
      </RouteLink>
      <RouteLink id="RL34">
        <From>
          <StopPointRef>6500K0237</StopPointRef>
        </From>
        <To>
          <StopPointRef>6500K0293</StopPointRef>
        </To>
        <Distance>303</Distance>
        <Direction>outbound</Direction>
      </RouteLink>
      <RouteLink id="RL35">
        <From>
          <StopPointRef>6500K0293</StopPointRef>
        </From>
        <To>
          <StopPointRef>6500K0304</StopPointRef>
        </To>
        <Distance>222</Distance>
        <Direction>outbound</Direction>
      </RouteLink>
      <RouteLink id="RL36">
        <From>
          <StopPointRef>6500K0304</StopPointRef>
        </From>
        <To>
          <StopPointRef>6500K0305</StopPointRef>
        </To>
        <Distance>146</Distance>
        <Direction>outbound</Direction>
      </RouteLink>
      <RouteLink id="RL37">
        <From>
          <StopPointRef>6500K0305</StopPointRef>
        </From>
        <To>
          <StopPointRef>6500K9301</StopPointRef>
        </To>
        <Distance>392</Distance>
        <Direction>outbound</Direction>
      </RouteLink>
    </RouteSection>
  </RouteSections>
  <Routes>
    <Route id="RT1">
      <PrivateCode>F034_34B-1</PrivateCode>
      <Description>Kirkcaldy Bus Station 7 - Kirkcaldy Bus Station</Description>
      <RouteSectionRef>RS1</RouteSectionRef>
    </Route>
  </Routes>
  <JourneyPatternSections>
    <JourneyPatternSection id="JPS1">
      <JourneyPatternTimingLink id="JPTL1">
        <From>
          <Activity>pickUpAndSetDown</Activity>
          <DynamicDestinationDisplay>Templehall</DynamicDestinationDisplay>
          <StopPointRef>6500K1307</StopPointRef>
          <TimingStatus>PTP</TimingStatus>
        </From>
        <To>
          <Activity>pickUpAndSetDown</Activity>
          <DynamicDestinationDisplay>Templehall</DynamicDestinationDisplay>
          <StopPointRef>6500K0303</StopPointRef>
          <TimingStatus>OTH</TimingStatus>
        </To>
        <RouteLinkRef>RL1</RouteLinkRef>
        <RunTime>PT2M0S</RunTime>
      </JourneyPatternTimingLink>
      <JourneyPatternTimingLink id="JPTL2">
        <From>
          <Activity>pickUpAndSetDown</Activity>
          <DynamicDestinationDisplay>Templehall</DynamicDestinationDisplay>
          <StopPointRef>6500K0303</StopPointRef>
          <TimingStatus>OTH</TimingStatus>
        </From>
        <To>
          <Activity>pickUpAndSetDown</Activity>
          <DynamicDestinationDisplay>Templehall</DynamicDestinationDisplay>
          <StopPointRef>6500K0227</StopPointRef>
          <TimingStatus>OTH</TimingStatus>
        </To>
        <RouteLinkRef>RL2</RouteLinkRef>
        <RunTime>PT1M0S</RunTime>
      </JourneyPatternTimingLink>
      <JourneyPatternTimingLink id="JPTL3">
        <From>
          <Activity>pickUpAndSetDown</Activity>
          <DynamicDestinationDisplay>Templehall</DynamicDestinationDisplay>
          <StopPointRef>6500K0227</StopPointRef>
          <TimingStatus>OTH</TimingStatus>
        </From>
        <To>
          <Activity>pickUpAndSetDown</Activity>
          <DynamicDestinationDisplay>Templehall</DynamicDestinationDisplay>
          <StopPointRef>6500K0221</StopPointRef>
          <TimingStatus>OTH</TimingStatus>
        </To>
        <RouteLinkRef>RL3</RouteLinkRef>
        <RunTime>PT1M0S</RunTime>
      </JourneyPatternTimingLink>
      <JourneyPatternTimingLink id="JPTL4">
        <From>
          <Activity>pickUpAndSetDown</Activity>
          <DynamicDestinationDisplay>Templehall</DynamicDestinationDisplay>
          <StopPointRef>6500K0221</StopPointRef>
          <TimingStatus>OTH</TimingStatus>
        </From>
        <To>
          <Activity>pickUpAndSetDown</Activity>
          <DynamicDestinationDisplay>Templehall</DynamicDestinationDisplay>
          <StopPointRef>6500K0219</StopPointRef>
          <TimingStatus>OTH</TimingStatus>
        </To>
        <RouteLinkRef>RL4</RouteLinkRef>
        <RunTime>PT1M0S</RunTime>
      </JourneyPatternTimingLink>
      <JourneyPatternTimingLink id="JPTL5">
        <From>
          <Activity>pickUpAndSetDown</Activity>
          <DynamicDestinationDisplay>Templehall</DynamicDestinationDisplay>
          <StopPointRef>6500K0219</StopPointRef>
          <TimingStatus>OTH</TimingStatus>
        </From>
        <To>
          <Activity>pickUpAndSetDown</Activity>
          <DynamicDestinationDisplay>Templehall</DynamicDestinationDisplay>
          <StopPointRef>6500K0218</StopPointRef>
          <TimingStatus>OTH</TimingStatus>
        </To>
        <RouteLinkRef>RL5</RouteLinkRef>
        <RunTime>PT0M0S</RunTime>
      </JourneyPatternTimingLink>
      <JourneyPatternTimingLink id="JPTL6">
        <From>
          <Activity>pickUpAndSetDown</Activity>
          <DynamicDestinationDisplay>Templehall</DynamicDestinationDisplay>
          <StopPointRef>6500K0218</StopPointRef>
          <TimingStatus>OTH</TimingStatus>
        </From>
        <To>
          <Activity>pickUpAndSetDown</Activity>
          <DynamicDestinationDisplay>Templehall</DynamicDestinationDisplay>
          <StopPointRef>6500K0216</StopPointRef>
          <TimingStatus>PTP</TimingStatus>
        </To>
        <RouteLinkRef>RL6</RouteLinkRef>
        <RunTime>PT1M0S</RunTime>
      </JourneyPatternTimingLink>
      <JourneyPatternTimingLink id="JPTL7">
        <From>
          <Activity>pickUpAndSetDown</Activity>
          <DynamicDestinationDisplay>Templehall</DynamicDestinationDisplay>
          <StopPointRef>6500K0216</StopPointRef>
          <TimingStatus>PTP</TimingStatus>
        </From>
        <To>
          <Activity>pickUpAndSetDown</Activity>
          <DynamicDestinationDisplay>Templehall</DynamicDestinationDisplay>
          <StopPointRef>6500K0213</StopPointRef>
          <TimingStatus>OTH</TimingStatus>
        </To>
        <RouteLinkRef>RL7</RouteLinkRef>
        <RunTime>PT2M0S</RunTime>
      </JourneyPatternTimingLink>
      <JourneyPatternTimingLink id="JPTL8">
        <From>
          <Activity>pickUpAndSetDown</Activity>
          <DynamicDestinationDisplay>Templehall</DynamicDestinationDisplay>
          <StopPointRef>6500K0213</StopPointRef>
          <TimingStatus>OTH</TimingStatus>
        </From>
        <To>
          <Activity>pickUpAndSetDown</Activity>
          <DynamicDestinationDisplay>Templehall</DynamicDestinationDisplay>
          <StopPointRef>6500K0211</StopPointRef>
          <TimingStatus>OTH</TimingStatus>
        </To>
        <RouteLinkRef>RL8</RouteLinkRef>
        <RunTime>PT1M0S</RunTime>
      </JourneyPatternTimingLink>
      <JourneyPatternTimingLink id="JPTL9">
        <From>
          <Activity>pickUpAndSetDown</Activity>
          <DynamicDestinationDisplay>Templehall</DynamicDestinationDisplay>
          <StopPointRef>6500K0211</StopPointRef>
          <TimingStatus>OTH</TimingStatus>
        </From>
        <To>
          <Activity>pickUpAndSetDown</Activity>
          <DynamicDestinationDisplay>Templehall</DynamicDestinationDisplay>
          <StopPointRef>6500K0086</StopPointRef>
          <TimingStatus>OTH</TimingStatus>
        </To>
        <RouteLinkRef>RL9</RouteLinkRef>
        <RunTime>PT1M0S</RunTime>
      </JourneyPatternTimingLink>
      <JourneyPatternTimingLink id="JPTL10">
        <From>
          <Activity>pickUpAndSetDown</Activity>
          <DynamicDestinationDisplay>Templehall</DynamicDestinationDisplay>
          <StopPointRef>6500K0086</StopPointRef>
          <TimingStatus>OTH</TimingStatus>
        </From>
        <To>
          <Activity>pickUpAndSetDown</Activity>
          <DynamicDestinationDisplay>Bus Station</DynamicDestinationDisplay>
          <StopPointRef>6500K0084</StopPointRef>
          <TimingStatus>PTP</TimingStatus>
        </To>
        <RouteLinkRef>RL10</RouteLinkRef>
        <RunTime>PT1M0S</RunTime>
      </JourneyPatternTimingLink>
      <JourneyPatternTimingLink id="JPTL11">
        <From>
          <Activity>pickUpAndSetDown</Activity>
          <DynamicDestinationDisplay>Bus Station</DynamicDestinationDisplay>
          <StopPointRef>6500K0084</StopPointRef>
          <TimingStatus>PTP</TimingStatus>
        </From>
        <To>
          <Activity>pickUpAndSetDown</Activity>
          <DynamicDestinationDisplay>Bus Station</DynamicDestinationDisplay>
          <StopPointRef>6500K0082</StopPointRef>
          <TimingStatus>OTH</TimingStatus>
        </To>
        <RouteLinkRef>RL11</RouteLinkRef>
        <RunTime>PT1M0S</RunTime>
      </JourneyPatternTimingLink>
      <JourneyPatternTimingLink id="JPTL12">
        <From>
          <Activity>pickUpAndSetDown</Activity>
          <DynamicDestinationDisplay>Bus Station</DynamicDestinationDisplay>
          <StopPointRef>6500K0082</StopPointRef>
          <TimingStatus>OTH</TimingStatus>
        </From>
        <To>
          <Activity>pickUpAndSetDown</Activity>
          <DynamicDestinationDisplay>Bus Station</DynamicDestinationDisplay>
          <StopPointRef>6500K1087</StopPointRef>
          <TimingStatus>OTH</TimingStatus>
        </To>
        <RouteLinkRef>RL12</RouteLinkRef>
        <RunTime>PT1M0S</RunTime>
      </JourneyPatternTimingLink>
      <JourneyPatternTimingLink id="JPTL13">
        <From>
          <Activity>pickUpAndSetDown</Activity>
          <DynamicDestinationDisplay>Bus Station</DynamicDestinationDisplay>
          <StopPointRef>6500K1087</StopPointRef>
          <TimingStatus>OTH</TimingStatus>
        </From>
        <To>
          <Activity>pickUpAndSetDown</Activity>
          <DynamicDestinationDisplay>Bus Station</DynamicDestinationDisplay>
          <StopPointRef>6500K1497</StopPointRef>
          <TimingStatus>OTH</TimingStatus>
        </To>
        <RouteLinkRef>RL13</RouteLinkRef>
        <RunTime>PT0M0S</RunTime>
      </JourneyPatternTimingLink>
      <JourneyPatternTimingLink id="JPTL14">
        <From>
          <Activity>pickUpAndSetDown</Activity>
          <DynamicDestinationDisplay>Bus Station</DynamicDestinationDisplay>
          <StopPointRef>6500K1497</StopPointRef>
          <TimingStatus>OTH</TimingStatus>
        </From>
        <To>
          <Activity>pickUpAndSetDown</Activity>
          <DynamicDestinationDisplay>Bus Station</DynamicDestinationDisplay>
          <StopPointRef>6500K1089</StopPointRef>
          <TimingStatus>OTH</TimingStatus>
        </To>
        <RouteLinkRef>RL14</RouteLinkRef>
        <RunTime>PT0M0S</RunTime>
      </JourneyPatternTimingLink>
      <JourneyPatternTimingLink id="JPTL15">
        <From>
          <Activity>pickUpAndSetDown</Activity>
          <DynamicDestinationDisplay>Bus Station</DynamicDestinationDisplay>
          <StopPointRef>6500K1089</StopPointRef>
          <TimingStatus>OTH</TimingStatus>
        </From>
        <To>
          <Activity>pickUpAndSetDown</Activity>
          <DynamicDestinationDisplay>Bus Station</DynamicDestinationDisplay>
          <StopPointRef>6500K0057</StopPointRef>
          <TimingStatus>PTP</TimingStatus>
        </To>
        <RouteLinkRef>RL15</RouteLinkRef>
        <RunTime>PT1M0S</RunTime>
      </JourneyPatternTimingLink>
      <JourneyPatternTimingLink id="JPTL16">
        <From>
          <Activity>pickUpAndSetDown</Activity>
          <DynamicDestinationDisplay>Bus Station</DynamicDestinationDisplay>
          <StopPointRef>6500K0057</StopPointRef>
          <TimingStatus>PTP</TimingStatus>
        </From>
        <To>
          <Activity>pickUpAndSetDown</Activity>
          <DynamicDestinationDisplay>Bus Station</DynamicDestinationDisplay>
          <StopPointRef>6500K0041</StopPointRef>
          <TimingStatus>OTH</TimingStatus>
        </To>
        <RouteLinkRef>RL16</RouteLinkRef>
        <RunTime>PT1M0S</RunTime>
      </JourneyPatternTimingLink>
      <JourneyPatternTimingLink id="JPTL17">
        <From>
          <Activity>pickUpAndSetDown</Activity>
          <DynamicDestinationDisplay>Bus Station</DynamicDestinationDisplay>
          <StopPointRef>6500K0041</StopPointRef>
          <TimingStatus>OTH</TimingStatus>
        </From>
        <To>
          <Activity>pickUpAndSetDown</Activity>
          <DynamicDestinationDisplay>Bus Station</DynamicDestinationDisplay>
          <StopPointRef>6500K0034</StopPointRef>
          <TimingStatus>OTH</TimingStatus>
        </To>
        <RouteLinkRef>RL17</RouteLinkRef>
        <RunTime>PT0M0S</RunTime>
      </JourneyPatternTimingLink>
      <JourneyPatternTimingLink id="JPTL18">
        <From>
          <Activity>pickUpAndSetDown</Activity>
          <DynamicDestinationDisplay>Bus Station</DynamicDestinationDisplay>
          <StopPointRef>6500K0034</StopPointRef>
          <TimingStatus>OTH</TimingStatus>
        </From>
        <To>
          <Activity>pickUpAndSetDown</Activity>
          <DynamicDestinationDisplay>Bus Station</DynamicDestinationDisplay>
          <StopPointRef>6500K0065</StopPointRef>
          <TimingStatus>OTH</TimingStatus>
        </To>
        <RouteLinkRef>RL18</RouteLinkRef>
        <RunTime>PT0M0S</RunTime>
      </JourneyPatternTimingLink>
      <JourneyPatternTimingLink id="JPTL19">
        <From>
          <Activity>pickUpAndSetDown</Activity>
          <DynamicDestinationDisplay>Bus Station</DynamicDestinationDisplay>
          <StopPointRef>6500K0065</StopPointRef>
          <TimingStatus>OTH</TimingStatus>
        </From>
        <To>
          <Activity>pickUpAndSetDown</Activity>
          <DynamicDestinationDisplay>Bus Station</DynamicDestinationDisplay>
          <StopPointRef>6500K0070</StopPointRef>
          <TimingStatus>OTH</TimingStatus>
        </To>
        <RouteLinkRef>RL19</RouteLinkRef>
        <RunTime>PT1M0S</RunTime>
      </JourneyPatternTimingLink>
      <JourneyPatternTimingLink id="JPTL20">
        <From>
          <Activity>pickUpAndSetDown</Activity>
          <DynamicDestinationDisplay>Bus Station</DynamicDestinationDisplay>
          <StopPointRef>6500K0070</StopPointRef>
          <TimingStatus>OTH</TimingStatus>
        </From>
        <To>
          <Activity>pickUpAndSetDown</Activity>
          <DynamicDestinationDisplay>Bus Station</DynamicDestinationDisplay>
          <StopPointRef>6500K9026</StopPointRef>
          <TimingStatus>OTH</TimingStatus>
        </To>
        <RouteLinkRef>RL20</RouteLinkRef>
        <RunTime>PT1M0S</RunTime>
      </JourneyPatternTimingLink>
      <JourneyPatternTimingLink id="JPTL21">
        <From>
          <Activity>pickUpAndSetDown</Activity>
          <DynamicDestinationDisplay>Bus Station</DynamicDestinationDisplay>
          <StopPointRef>6500K9026</StopPointRef>
          <TimingStatus>OTH</TimingStatus>
        </From>
        <To>
          <Activity>pickUpAndSetDown</Activity>
          <DynamicDestinationDisplay>Bus Station</DynamicDestinationDisplay>
          <StopPointRef>6500K1096</StopPointRef>
          <TimingStatus>OTH</TimingStatus>
        </To>
        <RouteLinkRef>RL21</RouteLinkRef>
        <RunTime>PT0M0S</RunTime>
      </JourneyPatternTimingLink>
      <JourneyPatternTimingLink id="JPTL22">
        <From>
          <Activity>pickUpAndSetDown</Activity>
          <DynamicDestinationDisplay>Bus Station</DynamicDestinationDisplay>
          <StopPointRef>6500K1096</StopPointRef>
          <TimingStatus>OTH</TimingStatus>
        </From>
        <To>
          <Activity>pickUpAndSetDown</Activity>
          <DynamicDestinationDisplay>Bus Station</DynamicDestinationDisplay>
          <StopPointRef>6500K1094</StopPointRef>
          <TimingStatus>OTH</TimingStatus>
        </To>
        <RouteLinkRef>RL22</RouteLinkRef>
        <RunTime>PT1M0S</RunTime>
      </JourneyPatternTimingLink>
      <JourneyPatternTimingLink id="JPTL23">
        <From>
          <Activity>pickUpAndSetDown</Activity>
          <DynamicDestinationDisplay>Bus Station</DynamicDestinationDisplay>
          <StopPointRef>6500K1094</StopPointRef>
          <TimingStatus>OTH</TimingStatus>
        </From>
        <To>
          <Activity>pickUpAndSetDown</Activity>
          <DynamicDestinationDisplay>Bus Station</DynamicDestinationDisplay>
          <StopPointRef>6500K1093</StopPointRef>
          <TimingStatus>OTH</TimingStatus>
        </To>
        <RouteLinkRef>RL23</RouteLinkRef>
        <RunTime>PT1M0S</RunTime>
      </JourneyPatternTimingLink>
      <JourneyPatternTimingLink id="JPTL24">
        <From>
          <Activity>pickUpAndSetDown</Activity>
          <DynamicDestinationDisplay>Bus Station</DynamicDestinationDisplay>
          <StopPointRef>6500K1093</StopPointRef>
          <TimingStatus>OTH</TimingStatus>
        </From>
        <To>
          <Activity>pickUpAndSetDown</Activity>
          <DynamicDestinationDisplay>Bus Station</DynamicDestinationDisplay>
          <StopPointRef>6500K1091</StopPointRef>
          <TimingStatus>OTH</TimingStatus>
        </To>
        <RouteLinkRef>RL24</RouteLinkRef>
        <RunTime>PT0M0S</RunTime>
      </JourneyPatternTimingLink>
      <JourneyPatternTimingLink id="JPTL25">
        <From>
          <Activity>pickUpAndSetDown</Activity>
          <DynamicDestinationDisplay>Bus Station</DynamicDestinationDisplay>
          <StopPointRef>6500K1091</StopPointRef>
          <TimingStatus>OTH</TimingStatus>
        </From>
        <To>
          <Activity>pickUpAndSetDown</Activity>
          <DynamicDestinationDisplay>Bus Station</DynamicDestinationDisplay>
          <StopPointRef>6500K0087</StopPointRef>
          <TimingStatus>PTP</TimingStatus>
        </To>
        <RouteLinkRef>RL25</RouteLinkRef>
        <RunTime>PT1M0S</RunTime>
      </JourneyPatternTimingLink>
      <JourneyPatternTimingLink id="JPTL26">
        <From>
          <Activity>pickUpAndSetDown</Activity>
          <DynamicDestinationDisplay>Bus Station</DynamicDestinationDisplay>
          <StopPointRef>6500K0087</StopPointRef>
          <TimingStatus>PTP</TimingStatus>
        </From>
        <To>
          <Activity>pickUpAndSetDown</Activity>
          <DynamicDestinationDisplay>Bus Station</DynamicDestinationDisplay>
          <StopPointRef>6500K0090</StopPointRef>
          <TimingStatus>OTH</TimingStatus>
        </To>
        <RouteLinkRef>RL26</RouteLinkRef>
        <RunTime>PT0M0S</RunTime>
      </JourneyPatternTimingLink>
      <JourneyPatternTimingLink id="JPTL27">
        <From>
          <Activity>pickUpAndSetDown</Activity>
          <DynamicDestinationDisplay>Bus Station</DynamicDestinationDisplay>
          <StopPointRef>6500K0090</StopPointRef>
          <TimingStatus>OTH</TimingStatus>
        </From>
        <To>
          <Activity>pickUpAndSetDown</Activity>
          <DynamicDestinationDisplay>Bus Station</DynamicDestinationDisplay>
          <StopPointRef>6500K0091</StopPointRef>
          <TimingStatus>OTH</TimingStatus>
        </To>
        <RouteLinkRef>RL27</RouteLinkRef>
        <RunTime>PT1M0S</RunTime>
      </JourneyPatternTimingLink>
      <JourneyPatternTimingLink id="JPTL28">
        <From>
          <Activity>pickUpAndSetDown</Activity>
          <DynamicDestinationDisplay>Bus Station</DynamicDestinationDisplay>
          <StopPointRef>6500K0091</StopPointRef>
          <TimingStatus>OTH</TimingStatus>
        </From>
        <To>
          <Activity>pickUpAndSetDown</Activity>
          <DynamicDestinationDisplay>Bus Station</DynamicDestinationDisplay>
          <StopPointRef>6500K0094</StopPointRef>
          <TimingStatus>OTH</TimingStatus>
        </To>
        <RouteLinkRef>RL28</RouteLinkRef>
        <RunTime>PT1M0S</RunTime>
      </JourneyPatternTimingLink>
      <JourneyPatternTimingLink id="JPTL29">
        <From>
          <Activity>pickUpAndSetDown</Activity>
          <DynamicDestinationDisplay>Bus Station</DynamicDestinationDisplay>
          <StopPointRef>6500K0094</StopPointRef>
          <TimingStatus>OTH</TimingStatus>
        </From>
        <To>
          <Activity>pickUpAndSetDown</Activity>
          <DynamicDestinationDisplay>Bus Station</DynamicDestinationDisplay>
          <StopPointRef>6500K0096</StopPointRef>
          <TimingStatus>OTH</TimingStatus>
        </To>
        <RouteLinkRef>RL29</RouteLinkRef>
        <RunTime>PT0M0S</RunTime>
      </JourneyPatternTimingLink>
      <JourneyPatternTimingLink id="JPTL30">
        <From>
          <Activity>pickUpAndSetDown</Activity>
          <DynamicDestinationDisplay>Bus Station</DynamicDestinationDisplay>
          <StopPointRef>6500K0096</StopPointRef>
          <TimingStatus>OTH</TimingStatus>
        </From>
        <To>
          <Activity>pickUpAndSetDown</Activity>
          <DynamicDestinationDisplay>Bus Station</DynamicDestinationDisplay>
          <StopPointRef>6500K0230</StopPointRef>
          <TimingStatus>OTH</TimingStatus>
        </To>
        <RouteLinkRef>RL30</RouteLinkRef>
        <RunTime>PT1M0S</RunTime>
      </JourneyPatternTimingLink>
      <JourneyPatternTimingLink id="JPTL31">
        <From>
          <Activity>pickUpAndSetDown</Activity>
          <DynamicDestinationDisplay>Bus Station</DynamicDestinationDisplay>
          <StopPointRef>6500K0230</StopPointRef>
          <TimingStatus>OTH</TimingStatus>
        </From>
        <To>
          <Activity>pickUpAndSetDown</Activity>
          <DynamicDestinationDisplay>Bus Station</DynamicDestinationDisplay>
          <StopPointRef>6500K0233</StopPointRef>
          <TimingStatus>OTH</TimingStatus>
        </To>
        <RouteLinkRef>RL31</RouteLinkRef>
        <RunTime>PT0M0S</RunTime>
      </JourneyPatternTimingLink>
      <JourneyPatternTimingLink id="JPTL32">
        <From>
          <Activity>pickUpAndSetDown</Activity>
          <DynamicDestinationDisplay>Bus Station</DynamicDestinationDisplay>
          <StopPointRef>6500K0233</StopPointRef>
          <TimingStatus>OTH</TimingStatus>
        </From>
        <To>
          <Activity>pickUpAndSetDown</Activity>
          <DynamicDestinationDisplay>Bus Station</DynamicDestinationDisplay>
          <StopPointRef>6500K0235</StopPointRef>
          <TimingStatus>OTH</TimingStatus>
        </To>
        <RouteLinkRef>RL32</RouteLinkRef>
        <RunTime>PT1M0S</RunTime>
      </JourneyPatternTimingLink>
      <JourneyPatternTimingLink id="JPTL33">
        <From>
          <Activity>pickUpAndSetDown</Activity>
          <DynamicDestinationDisplay>Bus Station</DynamicDestinationDisplay>
          <StopPointRef>6500K0235</StopPointRef>
          <TimingStatus>OTH</TimingStatus>
        </From>
        <To>
          <Activity>pickUpAndSetDown</Activity>
          <DynamicDestinationDisplay>Bus Station</DynamicDestinationDisplay>
          <StopPointRef>6500K0237</StopPointRef>
          <TimingStatus>OTH</TimingStatus>
        </To>
        <RouteLinkRef>RL33</RouteLinkRef>
        <RunTime>PT1M0S</RunTime>
      </JourneyPatternTimingLink>
      <JourneyPatternTimingLink id="JPTL34">
        <From>
          <Activity>pickUpAndSetDown</Activity>
          <DynamicDestinationDisplay>Bus Station</DynamicDestinationDisplay>
          <StopPointRef>6500K0237</StopPointRef>
          <TimingStatus>OTH</TimingStatus>
        </From>
        <To>
          <Activity>pickUpAndSetDown</Activity>
          <DynamicDestinationDisplay>Bus Station</DynamicDestinationDisplay>
          <StopPointRef>6500K0293</StopPointRef>
          <TimingStatus>OTH</TimingStatus>
        </To>
        <RouteLinkRef>RL34</RouteLinkRef>
        <RunTime>PT1M0S</RunTime>
      </JourneyPatternTimingLink>
      <JourneyPatternTimingLink id="JPTL35">
        <From>
          <Activity>pickUpAndSetDown</Activity>
          <DynamicDestinationDisplay>Bus Station</DynamicDestinationDisplay>
          <StopPointRef>6500K0293</StopPointRef>
          <TimingStatus>OTH</TimingStatus>
        </From>
        <To>
          <Activity>pickUpAndSetDown</Activity>
          <DynamicDestinationDisplay>Bus Station</DynamicDestinationDisplay>
          <StopPointRef>6500K0304</StopPointRef>
          <TimingStatus>OTH</TimingStatus>
        </To>
        <RouteLinkRef>RL35</RouteLinkRef>
        <RunTime>PT1M0S</RunTime>
      </JourneyPatternTimingLink>
      <JourneyPatternTimingLink id="JPTL36">
        <From>
          <Activity>pickUpAndSetDown</Activity>
          <DynamicDestinationDisplay>Bus Station</DynamicDestinationDisplay>
          <StopPointRef>6500K0304</StopPointRef>
          <TimingStatus>OTH</TimingStatus>
        </From>
        <To>
          <Activity>pickUpAndSetDown</Activity>
          <DynamicDestinationDisplay>Bus Station</DynamicDestinationDisplay>
          <StopPointRef>6500K0305</StopPointRef>
          <TimingStatus>OTH</TimingStatus>
        </To>
        <RouteLinkRef>RL36</RouteLinkRef>
        <RunTime>PT0M0S</RunTime>
      </JourneyPatternTimingLink>
      <JourneyPatternTimingLink id="JPTL37">
        <From>
          <Activity>pickUpAndSetDown</Activity>
          <DynamicDestinationDisplay>Bus Station</DynamicDestinationDisplay>
          <StopPointRef>6500K0305</StopPointRef>
          <TimingStatus>OTH</TimingStatus>
        </From>
        <To>
          <Activity>pickUpAndSetDown</Activity>
          <DynamicDestinationDisplay>Bus Station</DynamicDestinationDisplay>
          <StopPointRef>6500K9301</StopPointRef>
          <TimingStatus>PTP</TimingStatus>
        </To>
        <RouteLinkRef>RL37</RouteLinkRef>
        <RunTime>PT1M0S</RunTime>
      </JourneyPatternTimingLink>
    </JourneyPatternSection>
  </JourneyPatternSections>
  <Operators>
    <Operator id="1">
      <NationalOperatorCode>SCFI</NationalOperatorCode>
      <OperatorCode>SCFI</OperatorCode>
      <OperatorShortName>Stagecoach</OperatorShortName>
      <OperatorNameOnLicence>Fife Scottish Omnibuses Ltd</OperatorNameOnLicence>
      <TradingName>Stagecoach East Scotland</TradingName>
      <LicenceNumber>PM0000004</LicenceNumber>
      <LicenceClassification>standardInternational</LicenceClassification>
    </Operator>
  </Operators>
  <Services>
    <Service>
      <ServiceCode>S_SC_SCFI_34B_1</ServiceCode>
      <Lines>
        <Line id="SL1">
          <LineName>34B</LineName>
        </Line>
      </Lines>
      <OperatingPeriod>
        <StartDate>2024-08-19</StartDate>
      </OperatingPeriod>
      <OperatingProfile>
        <RegularDayType>
          <DaysOfWeek>
            <MondayToFriday />
          </DaysOfWeek>
        </RegularDayType>
        <BankHolidayOperation>
          <DaysOfOperation>
            <GoodFriday />
            <LateSummerBankHolidayNotScotland />
            <EasterMonday />
            <SpringBank />
            <ChristmasEve />
          </DaysOfOperation>
          <DaysOfNonOperation>
            <ChristmasDay />
            <BoxingDay />
            <NewYearsDay />
            <Jan2ndScotland />
            <MayDay />
            <ChristmasDayHoliday />
            <BoxingDayHoliday />
            <NewYearsDayHoliday />
            <NewYearsEve />
          </DaysOfNonOperation>
        </BankHolidayOperation>
      </OperatingProfile>
      <RegisteredOperatorRef>1</RegisteredOperatorRef>
      <StopRequirements>
        <NoNewStopsRequired />
      </StopRequirements>
      <PublicUse>true</PublicUse>
      <Description>Kirkcaldy Bus Station - Kirkcaldy Retail Park</Description>
      <StandardService>
        <Origin>Kirkcaldy Bus Station</Origin>
        <Destination>Kirkcaldy Retail Park</Destination>
        <JourneyPattern id="JP1">
          <DestinationDisplay>Kirkcaldy Bus Station</DestinationDisplay>
          <Direction>outbound</Direction>
          <RouteRef>RT1</RouteRef>
          <JourneyPatternSectionRefs>JPS1</JourneyPatternSectionRefs>
        </JourneyPattern>
      </StandardService>
    </Service>
  </Services>
  <VehicleJourneys>
    <VehicleJourney SequenceNumber="38">
      <PrivateCode>F034_34BMTWHF:I:0:1:6UMzRIEfO5g</PrivateCode>
      <Direction>outbound</Direction>
      <OperatingProfile>
        <RegularDayType>
          <DaysOfWeek>
            <Monday />
            <Tuesday />
            <Wednesday />
            <Thursday />
            <Friday />
          </DaysOfWeek>
        </RegularDayType>
        <SpecialDaysOperation>
          <DaysOfNonOperation>
            <DateRange>
              <StartDate>2024-12-25</StartDate>
              <EndDate>2024-12-27</EndDate>
            </DateRange>
            <DateRange>
              <StartDate>2024-12-30</StartDate>
              <EndDate>2025-01-02</EndDate>
            </DateRange>
          </DaysOfNonOperation>
        </SpecialDaysOperation>
        <BankHolidayOperation>
          <DaysOfOperation>
            <GoodFriday />
            <LateSummerBankHolidayNotScotland />
            <EasterMonday />
            <SpringBank />
            <ChristmasEve />
          </DaysOfOperation>
          <DaysOfNonOperation>
            <ChristmasDay />
            <BoxingDay />
            <NewYearsDay />
            <Jan2ndScotland />
            <MayDay />
            <ChristmasDayHoliday />
            <BoxingDayHoliday />
            <NewYearsDayHoliday />
            <NewYearsEve />
          </DaysOfNonOperation>
        </BankHolidayOperation>
      </OperatingProfile>
      <VehicleJourneyCode>VJ38</VehicleJourneyCode>
      <ServiceRef>S_SC_SCFI_34B_1</ServiceRef>
      <LineRef>SL1</LineRef>
      <JourneyPatternRef>JP1</JourneyPatternRef>
      <DepartureTime>07:45:00</DepartureTime>
    </VehicleJourney>
    <VehicleJourney SequenceNumber="40">
      <PrivateCode>F034_34BMTWHF:I:0:2:6UMzRIEfO5g</PrivateCode>
      <Direction>outbound</Direction>
      <OperatingProfile>
        <RegularDayType>
          <DaysOfWeek>
            <Monday />
            <Tuesday />
            <Wednesday />
            <Thursday />
            <Friday />
          </DaysOfWeek>
        </RegularDayType>
        <SpecialDaysOperation>
          <DaysOfNonOperation>
            <DateRange>
              <StartDate>2024-12-25</StartDate>
              <EndDate>2024-12-27</EndDate>
            </DateRange>
            <DateRange>
              <StartDate>2024-12-30</StartDate>
              <EndDate>2025-01-02</EndDate>
            </DateRange>
          </DaysOfNonOperation>
        </SpecialDaysOperation>
        <BankHolidayOperation>
          <DaysOfOperation>
            <GoodFriday />
            <LateSummerBankHolidayNotScotland />
            <EasterMonday />
            <SpringBank />
            <ChristmasEve />
          </DaysOfOperation>
          <DaysOfNonOperation>
            <ChristmasDay />
            <BoxingDay />
            <NewYearsDay />
            <Jan2ndScotland />
            <MayDay />
            <ChristmasDayHoliday />
            <BoxingDayHoliday />
            <NewYearsDayHoliday />
            <NewYearsEve />
          </DaysOfNonOperation>
        </BankHolidayOperation>
      </OperatingProfile>
      <VehicleJourneyCode>VJ40</VehicleJourneyCode>
      <ServiceRef>S_SC_SCFI_34B_1</ServiceRef>
      <LineRef>SL1</LineRef>
      <JourneyPatternRef>JP1</JourneyPatternRef>
      <DepartureTime>08:15:00</DepartureTime>
    </VehicleJourney>
  </VehicleJourneys>
</TransXChange>